qcs/__init__.py
qcs/breakbarrier.py
qcs/gatefinder.py
qcs/qcs.py
qcs/slicer.py
qcs/workfuncs.py
quantum_circuit_slicer-0.0.8.dist-info/LICENSE
quantum_circuit_slicer-0.0.8.dist-info/METADATA
quantum_circuit_slicer-0.0.8.dist-info/WHEEL
quantum_circuit_slicer-0.0.8.dist-info/top_level.txt
quantum_circuit_slicer-0.0.8.dist-info/RECORD
