Metadata-Version: 2.1
Name: quantum-circuit-slicer
Version: 0.0.8
Summary: A circuit slicer addition to Qiskit to help developers with debugging
Home-page: https://github.com/SaraM92/Quantum-Circuit-Slicer
Author: Sara Ayman Metwalli
Author-email: sara@sfc.wide.ad.jp
License: UNKNOWN
Platform: UNKNOWN
Classifier: Programming Language :: Python :: 3
Classifier: License :: OSI Approved :: Apache Software License
Classifier: Operating System :: OS Independent
Requires-Python: >=3.7
License-File: LICENSE
